ascend/__init__.py
ascend/common/__init__.py
ascend/common/align.py
ascend/common/clip.py
ascend/common/const.py
ascend/common/graph.py
ascend/common/log.py
ascend/common/path.py
ascend/common/progressbar.py
ascend/data/__init__.py
ascend/data/arrayptr.py
ascend/data/ascendarray.py
ascend/data/tensor.py
ascend/image/__init__.py
ascend/image/colorspace.py
ascend/image/geome.py
ascend/image/misc.py
ascend/model/__init__.py
ascend/model/aipp.py
ascend/model/model.py
ascend/ops/__init__.py
ascend/ops/blas.py
ascend/ops/csc.py
ascend/ops/math.py
ascend/ops/op.py
ascend/ops/util.py
ascend/post_process/__init__.py
ascend/post_process/bbox_overlaps.py
ascend/post_process/class_names.py
ascend/post_process/color.py
ascend/post_process/image.py
ascend/post_process/nms.py
ascend/profiling/__init__.py
ascend/profiling/profiling.py
ascend/resource/__init__.py
ascend/resource/context.py
ascend/resource/mem.py
ascend/resource/multiprocess.py
ascend/video/__init__.py
ascend/video/frame.py
ascend/video/vdec.py
ascend/video/venc.py
ascend/video/video_capture.py
ascend/video/video_writer.py
ascendfly-1.4.dist-info/LICENSE
ascendfly-1.4.dist-info/METADATA
ascendfly-1.4.dist-info/WHEEL
ascendfly-1.4.dist-info/top_level.txt
ascendfly-1.4.dist-info/RECORD
